{"dataset_id": "7fcd8812-d0fe-11e7-8db2-a0369f7c647e", "dataset_version": "2ccaa115543c21e6658950d1cb8cc3038f14272f", "type": "directory", "children": [{"type": "file", "dataset_id": "7fcd8812-d0fe-11e7-8db2-a0369f7c647e", "dataset_version": "2ccaa115543c21e6658950d1cb8cc3038f14272f", "path": "sub-15/shen_fconn/sub-15_task-avmovie_run-2_bold.csv", "url": [], "extractors_used": [{"extractor_name": "metalad_core", "extractor_version": "1", "extraction_parameter": {}, "extraction_time": 1652340710.980897, "agent_name": "Stephan Heunis", "agent_email": "s.heunis@fz-juelich.de"}], "contentbytesize": 1650749, "name": "sub-15_task-avmovie_run-2_bold.csv"}, {"type": "file", "dataset_id": "7fcd8812-d0fe-11e7-8db2-a0369f7c647e", "dataset_version": "2ccaa115543c21e6658950d1cb8cc3038f14272f", "path": "sub-15/shen_fconn/sub-15_task-avmovie_run-1_bold.csv", "url": [], "extractors_used": [{"extractor_name": "metalad_core", "extractor_version": "1", "extraction_parameter": {}, "extraction_time": 1652340711.004228, "agent_name": "Stephan Heunis", "agent_email": "s.heunis@fz-juelich.de"}], "contentbytesize": 1688470, "name": "sub-15_task-avmovie_run-1_bold.csv"}, {"type": "file", "dataset_id": "7fcd8812-d0fe-11e7-8db2-a0369f7c647e", "dataset_version": "2ccaa115543c21e6658950d1cb8cc3038f14272f", "path": "sub-15/shen_fconn/sub-15_task-avmovie_run-3_bold.csv", "url": [], "extractors_used": [{"extractor_name": "metalad_core", "extractor_version": "1", "extraction_parameter": {}, "extraction_time": 1652340711.143272, "agent_name": "Stephan Heunis", "agent_email": "s.heunis@fz-juelich.de"}], "contentbytesize": 1639759, "name": "sub-15_task-avmovie_run-3_bold.csv"}, {"type": "file", "dataset_id": "7fcd8812-d0fe-11e7-8db2-a0369f7c647e", "dataset_version": "2ccaa115543c21e6658950d1cb8cc3038f14272f", "path": "sub-15/shen_fconn/sub-15_task-avmovie_run-4_bold.csv", "url": [], "extractors_used": [{"extractor_name": "metalad_core", "extractor_version": "1", "extraction_parameter": {}, "extraction_time": 1652340711.177464, "agent_name": "Stephan Heunis", "agent_email": "s.heunis@fz-juelich.de"}], "contentbytesize": 1826267, "name": "sub-15_task-avmovie_run-4_bold.csv"}, {"type": "file", "dataset_id": "7fcd8812-d0fe-11e7-8db2-a0369f7c647e", "dataset_version": "2ccaa115543c21e6658950d1cb8cc3038f14272f", "path": "sub-15/shen_fconn/sub-15_task-avmovie_run-5_bold.csv", "url": [], "extractors_used": [{"extractor_name": "metalad_core", "extractor_version": "1", "extraction_parameter": {}, "extraction_time": 1652340711.426817, "agent_name": "Stephan Heunis", "agent_email": "s.heunis@fz-juelich.de"}], "contentbytesize": 1729801, "name": "sub-15_task-avmovie_run-5_bold.csv"}, {"type": "file", "dataset_id": "7fcd8812-d0fe-11e7-8db2-a0369f7c647e", "dataset_version": "2ccaa115543c21e6658950d1cb8cc3038f14272f", "path": "sub-15/shen_fconn/sub-15_task-avmovie_run-6_bold.csv", "url": [], "extractors_used": [{"extractor_name": "metalad_core", "extractor_version": "1", "extraction_parameter": {}, "extraction_time": 1652340711.5990348, "agent_name": "Stephan Heunis", "agent_email": "s.heunis@fz-juelich.de"}], "contentbytesize": 1643464, "name": "sub-15_task-avmovie_run-6_bold.csv"}, {"type": "file", "dataset_id": "7fcd8812-d0fe-11e7-8db2-a0369f7c647e", "dataset_version": "2ccaa115543c21e6658950d1cb8cc3038f14272f", "path": "sub-15/shen_fconn/sub-15_task-avmovie_run-7_bold.csv", "url": [], "extractors_used": [{"extractor_name": "metalad_core", "extractor_version": "1", "extraction_parameter": {}, "extraction_time": 1652340711.7248168, "agent_name": "Stephan Heunis", "agent_email": "s.heunis@fz-juelich.de"}], "contentbytesize": 2029213, "name": "sub-15_task-avmovie_run-7_bold.csv"}, {"type": "file", "dataset_id": "7fcd8812-d0fe-11e7-8db2-a0369f7c647e", "dataset_version": "2ccaa115543c21e6658950d1cb8cc3038f14272f", "path": "sub-15/shen_fconn/sub-15_task-avmovie_run-8_bold.csv", "url": [], "extractors_used": [{"extractor_name": "metalad_core", "extractor_version": "1", "extraction_parameter": {}, "extraction_time": 1652340711.736081, "agent_name": "Stephan Heunis", "agent_email": "s.heunis@fz-juelich.de"}], "contentbytesize": 1265468, "name": "sub-15_task-avmovie_run-8_bold.csv"}], "path": "sub-15/shen_fconn", "name": "shen_fconn"}